blackfire_conprof/__init__.py
blackfire_conprof/auto.py
blackfire_conprof/log.py
blackfire_conprof/profiler.py
blackfire_conprof/version.py
blackfire_conprof/bootstrap/__init__.py
blackfire_conprof/bootstrap/sitecustomize.py
blackfire_conprof-1.2.6.dist-info/METADATA
blackfire_conprof-1.2.6.dist-info/WHEEL
blackfire_conprof-1.2.6.dist-info/entry_points.txt
blackfire_conprof-1.2.6.dist-info/top_level.txt
blackfire_conprof-1.2.6.dist-info/RECORD
